wagtail_personalisation/__init__.py
wagtail_personalisation/adapters.py
wagtail_personalisation/admin.py
wagtail_personalisation/admin_urls.py
wagtail_personalisation/blocks.py
wagtail_personalisation/config.py
wagtail_personalisation/forms.py
wagtail_personalisation/models.py
wagtail_personalisation/receivers.py
wagtail_personalisation/rules.py
wagtail_personalisation/utils.py
wagtail_personalisation/views.py
wagtail_personalisation/wagtail_hooks.py
wagtail_personalisation/locale/en/LC_MESSAGES/django.po
wagtail_personalisation/migrations/0001_initial.py
wagtail_personalisation/migrations/0002_auto_20161205_1623.py
wagtail_personalisation/migrations/0003_auto_20161206_1005.py
wagtail_personalisation/migrations/0004_segment_persistent.py
wagtail_personalisation/migrations/0005_userisloggedinrule.py
wagtail_personalisation/migrations/0006_segment_match_any.py
wagtail_personalisation/migrations/0007_dayrule.py
wagtail_personalisation/migrations/0008_devicerule.py
wagtail_personalisation/migrations/0009_auto_20170531_0428.py
wagtail_personalisation/migrations/0010_auto_20170531_1101.py
wagtail_personalisation/migrations/0011_personalisablepagemetadata.py
wagtail_personalisation/migrations/0012_remove_personalisablepagemetadata_is_segmented.py
wagtail_personalisation/migrations/0013_add_dynamic_static_to_segment.py
wagtail_personalisation/migrations/0015_static_users.py
wagtail_personalisation/migrations/0016_auto_20180125_0918.py
wagtail_personalisation/migrations/0017_segment_randomisation_percent.py
wagtail_personalisation/migrations/0018_segment_excluded_users.py
wagtail_personalisation/migrations/0019_auto_20180526_1425.py
wagtail_personalisation/migrations/0020_rules_delete_relatedqueryname.py
wagtail_personalisation/migrations/0021_personalisablepagemetadata_segment_set_on_delete_protect.py
wagtail_personalisation/migrations/0022_personalisablepagemetadata_canonical_protect.py
wagtail_personalisation-0.15.3.dist-info/DESCRIPTION.rst
wagtail_personalisation-0.15.3.dist-info/METADATA
wagtail_personalisation-0.15.3.dist-info/RECORD
wagtail_personalisation-0.15.3.dist-info/WHEEL
wagtail_personalisation-0.15.3.dist-info/metadata.json
wagtail_personalisation-0.15.3.dist-info/top_level.txt
