Metadata-Version: 2.1
Name: wagtail-personalisation
Version: 0.15.3
Summary: A Wagtail add-on for showing personalized content
Home-page: https://labdigital.nl/
Author: Lab Digital BV and others
Author-email: opensource@labdigital.nl
License: MIT
Platform: UNKNOWN
Classifier: Development Status :: 5 - Production/Stable
Classifier: Environment :: Web Environment
Classifier: Intended Audience :: Developers
Classifier: License :: OSI Approved :: BSD License
Classifier: Operating System :: OS Independent
Classifier: Programming Language :: Python :: 3
Classifier: Programming Language :: Python :: 3.6
Classifier: Framework :: Django
Classifier: Framework :: Django :: 2.0
Classifier: Topic :: Internet :: WWW/HTTP :: Site Management
Provides-Extra: docs
Provides-Extra: test
